vuc3.py
vuc3-0.0.3.dist-info/METADATA
vuc3-0.0.3.dist-info/WHEEL
vuc3-0.0.3.dist-info/entry_points.txt
vuc3-0.0.3.dist-info/top_level.txt
vuc3-0.0.3.dist-info/RECORD
