Metadata-Version: 2.1
Name: vuc3
Version: 0.0.3
Summary: effects of vaccines on COVID-19 infection and mortality
Home-page: https://github.com/y-takefuji/vuc3
Author: yoshiyasu takefuji
Author-email: takefuji@keio.jp
License: UNKNOWN
Project-URL: Bug Tracker, https://github.com/y-takefuji/vuc3
Platform: UNKNOWN
Classifier: Programming Language :: Python :: 3
Classifier: License :: OSI Approved :: MIT License
Classifier: Operating System :: OS Independent
Requires-Python: >=3.8
